pg_utils/__init__.py
pg_utils/_version.py
pg_utils/bin_counts/__init__.py
pg_utils/bin_counts/base.py
pg_utils/bin_counts/freedman_diaconis.py
pg_utils/column/__init__.py
pg_utils/column/base.py
pg_utils/column/plot/__init__.py
pg_utils/connection/__init__.py
pg_utils/connection/base.py
pg_utils/exception/__init__.py
pg_utils/exception/base.py
pg_utils/table/__init__.py
pg_utils/table/base.py
pg_utils/table/table.py
pg_utils/templates/bin_counts.j2
pg_utils/templates/describe.j2
pg_utils/templates/describe_column.j2
pg_utils/util/__init__.py
pg_utils-0.6.0.dist-info/DESCRIPTION.rst
pg_utils-0.6.0.dist-info/METADATA
pg_utils-0.6.0.dist-info/RECORD
pg_utils-0.6.0.dist-info/WHEEL
pg_utils-0.6.0.dist-info/metadata.json
pg_utils-0.6.0.dist-info/top_level.txt
