Metadata-Version: 2.0
Name: pg-utils
Version: 0.6.0
Summary: Utility libraries for working with PostgreSQL
Home-page: https://github.com/jackmaney/pg-utils
Author: Jack Maney
Author-email: jackmaney@gmail.com
License: MIT
Platform: UNKNOWN
Requires-Dist: jinja2
Requires-Dist: lazy-property (>=0.0.1)
Requires-Dist: pandas
Requires-Dist: psycopg2
Requires-Dist: six
Provides-Extra: graphics
Requires-Dist: seaborn; extra == 'graphics'
